{"nodes": [{"id": "home_x_t_src_db_registry_codec_ts", "label": "registry_codec.ts", "file_type": "code", "source_file": "/home/x/t/src/db/registry_codec.ts", "source_location": "L1"}, {"id": "registry_codec_protocolclass", "label": "protocolClass()", "file_type": "code", "source_file": "/home/x/t/src/db/registry_codec.ts", "source_location": "L18"}, {"id": "registry_codec_tobigintsafe", "label": "toBigIntSafe()", "file_type": "code", "source_file": "/home/x/t/src/db/registry_codec.ts", "source_location": "L27"}, {"id": "registry_codec_rehydratev3state", "label": "rehydrateV3State()", "file_type": "code", "source_file": "/home/x/t/src/db/registry_codec.ts", "source_location": "L32"}, {"id": "registry_codec_rehydratestatedata", "label": "rehydrateStateData()", "file_type": "code", "source_file": "/home/x/t/src/db/registry_codec.ts", "source_location": "L46"}, {"id": "registry_codec_stringifywithbigint", "label": "stringifyWithBigInt()", "file_type": "code", "source_file": "/home/x/t/src/db/registry_codec.ts", "source_location": "L63"}, {"id": "registry_codec_parsejson", "label": "parseJson()", "file_type": "code", "source_file": "/home/x/t/src/db/registry_codec.ts", "source_location": "L73"}, {"id": "registry_codec_lowercaseaddresslist", "label": "lowerCaseAddressList()", "file_type": "code", "source_file": "/home/x/t/src/db/registry_codec.ts", "source_location": "L84"}, {"id": "registry_codec_mappoolrow", "label": "mapPoolRow()", "file_type": "code", "source_file": "/home/x/t/src/db/registry_codec.ts", "source_location": "L90"}, {"id": "registry_codec_mappoolmetarow", "label": "mapPoolMetaRow()", "file_type": "code", "source_file": "/home/x/t/src/db/registry_codec.ts", "source_location": "L105"}, {"id": "registry_codec_mapstalepoolrow", "label": "mapStalePoolRow()", "file_type": "code", "source_file": "/home/x/t/src/db/registry_codec.ts", "source_location": "L118"}, {"id": "registry_codec_maparbhistoryrow", "label": "mapArbHistoryRow()", "file_type": "code", "source_file": "/home/x/t/src/db/registry_codec.ts", "source_location": "L127"}], "edges": [{"source": "home_x_t_src_db_registry_codec_ts", "target": "registry_codec_protocolclass", "relation": "contains", "confidence": "EXTRACTED", "source_file": "/home/x/t/src/db/registry_codec.ts", "source_location": "L18", "weight": 1.0}, {"source": "home_x_t_src_db_registry_codec_ts", "target": "registry_codec_tobigintsafe", "relation": "contains", "confidence": "EXTRACTED", "source_file": "/home/x/t/src/db/registry_codec.ts", "source_location": "L27", "weight": 1.0}, {"source": "home_x_t_src_db_registry_codec_ts", "target": "registry_codec_rehydratev3state", "relation": "contains", "confidence": "EXTRACTED", "source_file": "/home/x/t/src/db/registry_codec.ts", "source_location": "L32", "weight": 1.0}, {"source": "home_x_t_src_db_registry_codec_ts", "target": "registry_codec_rehydratestatedata", "relation": "contains", "confidence": "EXTRACTED", "source_file": "/home/x/t/src/db/registry_codec.ts", "source_location": "L46", "weight": 1.0}, {"source": "home_x_t_src_db_registry_codec_ts", "target": "registry_codec_stringifywithbigint", "relation": "contains", "confidence": "EXTRACTED", "source_file": "/home/x/t/src/db/registry_codec.ts", "source_location": "L63", "weight": 1.0}, {"source": "home_x_t_src_db_registry_codec_ts", "target": "registry_codec_parsejson", "relation": "contains", "confidence": "EXTRACTED", "source_file": "/home/x/t/src/db/registry_codec.ts", "source_location": "L73", "weight": 1.0}, {"source": "home_x_t_src_db_registry_codec_ts", "target": "registry_codec_lowercaseaddresslist", "relation": "contains", "confidence": "EXTRACTED", "source_file": "/home/x/t/src/db/registry_codec.ts", "source_location": "L84", "weight": 1.0}, {"source": "home_x_t_src_db_registry_codec_ts", "target": "registry_codec_mappoolrow", "relation": "contains", "confidence": "EXTRACTED", "source_file": "/home/x/t/src/db/registry_codec.ts", "source_location": "L90", "weight": 1.0}, {"source": "home_x_t_src_db_registry_codec_ts", "target": "registry_codec_mappoolmetarow", "relation": "contains", "confidence": "EXTRACTED", "source_file": "/home/x/t/src/db/registry_codec.ts", "source_location": "L105", "weight": 1.0}, {"source": "home_x_t_src_db_registry_codec_ts", "target": "registry_codec_mapstalepoolrow", "relation": "contains", "confidence": "EXTRACTED", "source_file": "/home/x/t/src/db/registry_codec.ts", "source_location": "L118", "weight": 1.0}, {"source": "home_x_t_src_db_registry_codec_ts", "target": "registry_codec_maparbhistoryrow", "relation": "contains", "confidence": "EXTRACTED", "source_file": "/home/x/t/src/db/registry_codec.ts", "source_location": "L127", "weight": 1.0}, {"source": "registry_codec_rehydratestatedata", "target": "registry_codec_protocolclass", "relation": "calls", "confidence": "EXTRACTED", "source_file": "/home/x/t/src/db/registry_codec.ts", "source_location": "L48", "weight": 1.0}, {"source": "registry_codec_rehydratestatedata", "target": "registry_codec_tobigintsafe", "relation": "calls", "confidence": "EXTRACTED", "source_file": "/home/x/t/src/db/registry_codec.ts", "source_location": "L50", "weight": 1.0}, {"source": "registry_codec_rehydratestatedata", "target": "registry_codec_rehydratev3state", "relation": "calls", "confidence": "EXTRACTED", "source_file": "/home/x/t/src/db/registry_codec.ts", "source_location": "L58", "weight": 1.0}, {"source": "registry_codec_mappoolrow", "target": "registry_codec_parsejson", "relation": "calls", "confidence": "EXTRACTED", "source_file": "/home/x/t/src/db/registry_codec.ts", "source_location": "L94", "weight": 1.0}, {"source": "registry_codec_mappoolrow", "target": "registry_codec_rehydratestatedata", "relation": "calls", "confidence": "EXTRACTED", "source_file": "/home/x/t/src/db/registry_codec.ts", "source_location": "L100", "weight": 1.0}, {"source": "registry_codec_mappoolmetarow", "target": "registry_codec_parsejson", "relation": "calls", "confidence": "EXTRACTED", "source_file": "/home/x/t/src/db/registry_codec.ts", "source_location": "L109", "weight": 1.0}, {"source": "registry_codec_mapstalepoolrow", "target": "registry_codec_parsejson", "relation": "calls", "confidence": "EXTRACTED", "source_file": "/home/x/t/src/db/registry_codec.ts", "source_location": "L122", "weight": 1.0}, {"source": "registry_codec_maparbhistoryrow", "target": "registry_codec_parsejson", "relation": "calls", "confidence": "EXTRACTED", "source_file": "/home/x/t/src/db/registry_codec.ts", "source_location": "L130", "weight": 1.0}], "raw_calls": [{"caller_nid": "registry_codec_protocolclass", "callee": "includes", "source_file": "/home/x/t/src/db/registry_codec.ts", "source_location": "L20"}, {"caller_nid": "registry_codec_protocolclass", "callee": "includes", "source_file": "/home/x/t/src/db/registry_codec.ts", "source_location": "L21"}, {"caller_nid": "registry_codec_protocolclass", "callee": "startsWith", "source_file": "/home/x/t/src/db/registry_codec.ts", "source_location": "L22"}, {"caller_nid": "registry_codec_protocolclass", "callee": "startsWith", "source_file": "/home/x/t/src/db/registry_codec.ts", "source_location": "L23"}, {"caller_nid": "registry_codec_tobigintsafe", "callee": "BigInt", "source_file": "/home/x/t/src/db/registry_codec.ts", "source_location": "L29"}, {"caller_nid": "registry_codec_rehydratev3state", "callee": "map", "source_file": "/home/x/t/src/db/registry_codec.ts", "source_location": "L36"}, {"caller_nid": "registry_codec_rehydratev3state", "callee": "entries", "source_file": "/home/x/t/src/db/registry_codec.ts", "source_location": "L36"}, {"caller_nid": "registry_codec_rehydratestatedata", "callee": "isArray", "source_file": "/home/x/t/src/db/registry_codec.ts", "source_location": "L53"}, {"caller_nid": "registry_codec_rehydratestatedata", "callee": "map", "source_file": "/home/x/t/src/db/registry_codec.ts", "source_location": "L54"}, {"caller_nid": "registry_codec_stringifywithbigint", "callee": "stringify", "source_file": "/home/x/t/src/db/registry_codec.ts", "source_location": "L64"}, {"caller_nid": "registry_codec_parsejson", "callee": "parse", "source_file": "/home/x/t/src/db/registry_codec.ts", "source_location": "L78"}, {"caller_nid": "registry_codec_lowercaseaddresslist", "callee": "map", "source_file": "/home/x/t/src/db/registry_codec.ts", "source_location": "L85"}]}