{"nodes": [{"id": "home_x_t_src_state_poll_univ2_ts", "label": "poll_univ2.ts", "file_type": "code", "source_file": "/home/x/t/src/state/poll_univ2.ts", "source_location": "L1"}, {"id": "poll_univ2_polluniv2", "label": "PollUniv2", "file_type": "code", "source_file": "/home/x/t/src/state/poll_univ2.ts", "source_location": "L26"}, {"id": "poll_univ2_polluniv2_constructor", "label": ".constructor()", "file_type": "code", "source_file": "/home/x/t/src/state/poll_univ2.ts", "source_location": "L31"}, {"id": "poll_univ2_polluniv2_poll", "label": ".poll()", "file_type": "code", "source_file": "/home/x/t/src/state/poll_univ2.ts", "source_location": "L45"}, {"id": "poll_univ2_polluniv2_start", "label": ".start()", "file_type": "code", "source_file": "/home/x/t/src/state/poll_univ2.ts", "source_location": "L103"}], "edges": [{"source": "home_x_t_src_state_poll_univ2_ts", "target": "home_x_t_src_state_uniswap_v2_ts", "relation": "imports_from", "confidence": "EXTRACTED", "source_file": "/home/x/t/src/state/poll_univ2.ts", "source_location": "L16", "weight": 1.0}, {"source": "home_x_t_src_state_poll_univ2_ts", "target": "home_x_t_src_state_normalizer_ts", "relation": "imports_from", "confidence": "EXTRACTED", "source_file": "/home/x/t/src/state/poll_univ2.ts", "source_location": "L17", "weight": 1.0}, {"source": "home_x_t_src_state_poll_univ2_ts", "target": "home_x_t_src_state_poller_base_ts", "relation": "imports_from", "confidence": "EXTRACTED", "source_file": "/home/x/t/src/state/poll_univ2.ts", "source_location": "L18", "weight": 1.0}, {"source": "home_x_t_src_state_poll_univ2_ts", "target": "poll_univ2_polluniv2", "relation": "contains", "confidence": "EXTRACTED", "source_file": "/home/x/t/src/state/poll_univ2.ts", "source_location": "L26", "weight": 1.0}, {"source": "poll_univ2_polluniv2", "target": "poll_univ2_polluniv2_constructor", "relation": "method", "confidence": "EXTRACTED", "source_file": "/home/x/t/src/state/poll_univ2.ts", "source_location": "L31", "weight": 1.0}, {"source": "poll_univ2_polluniv2", "target": "poll_univ2_polluniv2_poll", "relation": "method", "confidence": "EXTRACTED", "source_file": "/home/x/t/src/state/poll_univ2.ts", "source_location": "L45", "weight": 1.0}, {"source": "poll_univ2_polluniv2", "target": "poll_univ2_polluniv2_start", "relation": "method", "confidence": "EXTRACTED", "source_file": "/home/x/t/src/state/poll_univ2.ts", "source_location": "L103", "weight": 1.0}], "raw_calls": [{"caller_nid": "poll_univ2_polluniv2_constructor", "callee": "super", "source_file": "/home/x/t/src/state/poll_univ2.ts", "source_location": "L32"}, {"caller_nid": "poll_univ2_polluniv2_poll", "callee": "now", "source_file": "/home/x/t/src/state/poll_univ2.ts", "source_location": "L46"}, {"caller_nid": "poll_univ2_polluniv2_poll", "callee": "filter", "source_file": "/home/x/t/src/state/poll_univ2.ts", "source_location": "L49"}, {"caller_nid": "poll_univ2_polluniv2_poll", "callee": "getActivePoolsMeta", "source_file": "/home/x/t/src/state/poll_univ2.ts", "source_location": "L49"}, {"caller_nid": "poll_univ2_polluniv2_poll", "callee": "now", "source_file": "/home/x/t/src/state/poll_univ2.ts", "source_location": "L54"}, {"caller_nid": "poll_univ2_polluniv2_poll", "callee": "map", "source_file": "/home/x/t/src/state/poll_univ2.ts", "source_location": "L57"}, {"caller_nid": "poll_univ2_polluniv2_poll", "callee": "fetchMultipleV2States", "source_file": "/home/x/t/src/state/poll_univ2.ts", "source_location": "L60"}, {"caller_nid": "poll_univ2_polluniv2_poll", "callee": "toLowerCase", "source_file": "/home/x/t/src/state/poll_univ2.ts", "source_location": "L67"}, {"caller_nid": "poll_univ2_polluniv2_poll", "callee": "get", "source_file": "/home/x/t/src/state/poll_univ2.ts", "source_location": "L68"}, {"caller_nid": "poll_univ2_polluniv2_poll", "callee": "normalizeV2State", "source_file": "/home/x/t/src/state/poll_univ2.ts", "source_location": "L75"}, {"caller_nid": "poll_univ2_polluniv2_poll", "callee": "set", "source_file": "/home/x/t/src/state/poll_univ2.ts", "source_location": "L83"}, {"caller_nid": "poll_univ2_polluniv2_poll", "callee": "log", "source_file": "/home/x/t/src/state/poll_univ2.ts", "source_location": "L87"}, {"caller_nid": "poll_univ2_polluniv2_poll", "callee": "_completePass", "source_file": "/home/x/t/src/state/poll_univ2.ts", "source_location": "L93"}, {"caller_nid": "poll_univ2_polluniv2_start", "callee": "_startLoop", "source_file": "/home/x/t/src/state/poll_univ2.ts", "source_location": "L104"}]}